portilooplot/__init__.py
portilooplot/jupyter_plot.py
portilooplot/plot_learning_curve.py
portilooplot/web_assets/d3.bundle.js
portilooplot/web_assets/d3.js
portilooplot/web_assets/learning_curve.css
portilooplot/web_assets/learning_curve.js
portilooplot-0.0.4.dist-info/LICENSE.txt
portilooplot-0.0.4.dist-info/METADATA
portilooplot-0.0.4.dist-info/WHEEL
portilooplot-0.0.4.dist-info/top_level.txt
portilooplot-0.0.4.dist-info/RECORD
